textfmt-0.2.1.dist-info/licenses/LICENSE
textformat/__init__.py
textformat/progress.py
textformat/table.py
textformat/textformat.py
textformat/word_art.py
textfmt-0.2.1.dist-info/METADATA
textfmt-0.2.1.dist-info/WHEEL
textfmt-0.2.1.dist-info/top_level.txt
textfmt-0.2.1.dist-info/RECORD
