Metadata-Version: 2.4
Name: textfmt
Version: 0.2.1
Summary: Terminal Formatting for Humans
Author-email: Rihaan Meher <meherrihaan@gmail.com>
License: MIT
Project-URL: Homepage, https://github.com/sharktide/textformat
Requires-Python: >=3.6
License-File: LICENSE
Dynamic: license-file
